odoo/addons/purchase_merge/README.rst
odoo/addons/purchase_merge/__init__.py
odoo/addons/purchase_merge/__manifest__.py
odoo/addons/purchase_merge/i18n/es.po
odoo/addons/purchase_merge/i18n/it.po
odoo/addons/purchase_merge/i18n/pt_BR.po
odoo/addons/purchase_merge/i18n/purchase_merge.pot
odoo/addons/purchase_merge/readme/CONTRIBUTORS.md
odoo/addons/purchase_merge/readme/DESCRIPTION.md
odoo/addons/purchase_merge/readme/USAGE.md
odoo/addons/purchase_merge/security/ir.model.access.csv
odoo/addons/purchase_merge/static/description/icon.png
odoo/addons/purchase_merge/static/description/index.html
odoo/addons/purchase_merge/tests/__init__.py
odoo/addons/purchase_merge/tests/test_purchase_merge.py
odoo/addons/purchase_merge/wizard/__init__.py
odoo/addons/purchase_merge/wizard/purchase_merge.py
odoo/addons/purchase_merge/wizard/purchase_merge_views.xml
odoo_addon_purchase_merge-17.0.1.0.0.2.dist-info/METADATA
odoo_addon_purchase_merge-17.0.1.0.0.2.dist-info/WHEEL
odoo_addon_purchase_merge-17.0.1.0.0.2.dist-info/top_level.txt
odoo_addon_purchase_merge-17.0.1.0.0.2.dist-info/RECORD
